[
    [
        {
            "type": "title",
            "content": {
                "title_content": [
                    {
                        "type": "text",
                        "content": "回声贩卖者"
                    }
                ],
                "level": 1
            },
            "bbox": [
                149,
                86,
                238,
                99
            ]
        },
        {
            "type": "paragraph",
            "content": {
                "paragraph_content": [
                    {
                        "type": "text",
                        "content": "在时间尚未被切割成秒与分的年代，存在一种职业，名为“回声贩卖者”。他们穿行于尚未凝固的黎明与黄昏之间，收集那些被遗忘在峡谷里的叹息、被婴儿遗弃的第一声啼哭、以及石板路上马车轮子碾过时留下的余韵。这些回声被装进特制的琉璃瓶中，瓶身会随着回声的情感浓度而改变颜色。据说，最珍贵的回声来自那些从未发生过对话的沉默——当两个人站在即将分离的十字路口，所有未说出口的话凝结成一种透明的、近乎真空的声波，贩卖者只有在自己也经历过同等的沉默时，才能将其捕获。后来，人类发明了留声机，回声贩卖者便逐渐消失在声音的缝隙里，只剩下偶尔在老旧建筑的墙角，还能听见他们遗留的瓶子里传来若有若无的震颤——那是某个从未被讲述的故事，正在试图找到自己的第一个听众。"
                    }
                ]
            },
            "bbox": [
                149,
                104,
                850,
                250
            ]
        }
    ]
]